rcon.py
mseep_minecraft_docker_mcp-0.1.4.dist-info/METADATA
mseep_minecraft_docker_mcp-0.1.4.dist-info/WHEEL
mseep_minecraft_docker_mcp-0.1.4.dist-info/top_level.txt
mseep_minecraft_docker_mcp-0.1.4.dist-info/RECORD
